kcws
kcws/common
kcws/config
kcws/pid
