Metadata-Version: 1.2
Name: kcws
Version: 3.34
Summary: kcwebs作为web开发而设计的高性能框架
Home-page: https://docs.kwebapp.cn/index/index/2
Author: 百里-坤坤
Author-email: kcwebs@kwebapp.cn
Maintainer: 坤坤
Maintainer-email: fk1402936534@qq.com
License: MIT License
Keywords: kcws3.34
Platform: UNKNOWN
